sedcreator
