Metadata-Version: 2.1
Name: sedcreator
Version: 0.9.7
Summary: sedcreator is a package that has two main classes, SedFluxer and SedFitter. SedFluxer performs aperture photometry on a given image, coordinates and aperture size. It has a number of functions to print useful information and to plot the image together with apertures. SedFitter fits observations to a grid of models following the Zhang and Tan (2018) radiative transfer models.
Home-page: https://github.com/fedriani/sedcreator
Author: Ruben Fedriani
Author-email: ruben.fedriani@gmail.com
License: GNU General Public License v3.0
Project-URL: Bug Tracker, https://github.com/fedriani/sedcreator/issues
Classifier: Topic :: Scientific/Engineering :: Astronomy
Classifier: Programming Language :: Python
Classifier: Programming Language :: Python :: 3
Requires-Python: >=3.6
License-File: LICENSE.txt
Requires-Dist: astropy (>=4.3.1)
Requires-Dist: astroquery (>=0.4.3)
Requires-Dist: matplotlib
Requires-Dist: numpy
Requires-Dist: photutils (>=1.3.0)
Requires-Dist: scipy (>=1.5.0)
Requires-Dist: setuptools
Requires-Dist: tqdm
